kmpico/__init__.py
kmpico-0.1.0.dist-info/METADATA
kmpico-0.1.0.dist-info/WHEEL
kmpico-0.1.0.dist-info/top_level.txt
kmpico-0.1.0.dist-info/RECORD
