Metadata-Version: 2.4
Name: kmpico
Version: 0.1.0
Summary: kyungmoon_A user-friendly MicroPython library for Raspberry Pi Pico to control various sensors and modules.
Author-email: limtae <edh427@sen.go.kr>
License: MIT License
Keywords: micropython,raspberry pi pico,pico,sensors,electronics
Classifier: Development Status :: 4 - Beta
Classifier: Intended Audience :: Developers
Classifier: License :: OSI Approved :: MIT License
Classifier: Programming Language :: Python :: 3
Classifier: Programming Language :: Python :: Implementation :: MicroPython
Classifier: Topic :: Software Development :: Libraries
Classifier: Topic :: System :: Hardware
Requires-Python: >=3.6
